{
  "timestamp": "2026-01-10T01:53:25.862119Z",
  "symbol": "EURJPY",
  "timeframe": "H1",
  "price": {
    "bid": 183.695,
    "ask": 183.766,
    "last": 0.0
  },
  "sentiment": "BULLISH",
  "analysis": "Market analysis indicates positive momentum favoring buyers. RSI at 68.31 remains in neutral territory. Money Flow Index at 53.44 suggests balanced volume distribution. MACD showing trend transition, awaiting confirmation. Price extended above Bollinger upper band, reversal risk elevated. Price structure supports bullish continuation with MA and SAR confirmation. Ichimoku cloud analysis supports bullish bias.",
  "indicators": {
    "rsi": {
      "value": 68.31,
      "condition": "NEUTRAL",
      "signal": "HOLD"
    },
    "mfi": {
      "value": 53.44,
      "condition": "NEUTRAL",
      "signal": "HOLD"
    },
    "stochastic": {
      "main": 39.13,
      "signal": 47.8,
      "condition": "NEUTRAL",
      "signal_type": "HOLD"
    },
    "macd": {
      "main": -0.00996,
      "signal": -0.03787,
      "divergence": 0.02791,
      "histogram": "POSITIVE",
      "trend": "BULLISH"
    },
    "bollinger_bands": {
      "upper": 183.62197,
      "middle": 183.3306,
      "lower": 183.03923,
      "price_position": "ABOVE_UPPER",
      "bandwidth": 0.58274
    },
    "moving_average": {
      "value": 183.40921,
      "price_position": "ABOVE",
      "signal": "BULLISH"
    },
    "parabolic_sar": {
      "value": 183.646,
      "price_position": "ABOVE",
      "trend": "UPTREND"
    },
    "ichimoku": {
      "tenkan_sen": 183.4415,
      "kijun_sen": 183.228,
      "price_vs_tenkan": "ABOVE",
      "price_vs_kijun": "ABOVE",
      "tk_cross": "BULLISH"
    }
  },
  "indicator_insights": {
    "rsi": "Strong momentum at 68.3, trend continuation favored.",
    "mfi": "Balanced volume flow at 53.4, institutional activity moderate.",
    "stochastic": "Mid-range at 39.1, no extreme momentum detected.",
    "macd": "Early bullish crossover below zero. Recovery phase initiated, watch for confirmation.",
    "bollinger_bands": "Price extended above upper band. Parabolic move detected, exhaustion imminent.",
    "moving_average": "Price 0.16% above MA. Uptrend confirmed, MA acting as dynamic support.",
    "parabolic_sar": "SAR positioned below price at 183.64600. Uptrend active, trailing stop recommended.",
    "ichimoku": "Price above cloud components. Strong bullish structure, all systems aligned for longs."
  },
  "signals": {
    "primary": "BUY",
    "strength": "MODERATE",
    "recommendation": "CONSIDER_LONG"
  }
}