{
  "timestamp": "2025-12-15T01:56:37.095883Z",
  "symbol": "EURUSD",
  "timeframe": "H1",
  "price": {
    "bid": 1.1739600000000001,
    "ask": 1.17416,
    "last": 0.0
  },
  "sentiment": "NEUTRAL",
  "analysis": "Market analysis indicates balanced conditions with no clear directional bias. RSI at 55.02 remains in neutral territory. Money Flow Index at 57.07 suggests balanced volume distribution. MACD showing trend transition, awaiting confirmation. Price maintaining above Bollinger middle band, uptrend intact. Price action mixed with conflicting signals from trend indicators. Ichimoku cloud analysis supports bullish bias.",
  "indicators": {
    "rsi": {
      "value": 55.02,
      "condition": "NEUTRAL",
      "signal": "HOLD"
    },
    "mfi": {
      "value": 57.07,
      "condition": "NEUTRAL",
      "signal": "HOLD"
    },
    "stochastic": {
      "main": 49.47,
      "signal": 55.26,
      "condition": "NEUTRAL",
      "signal_type": "HOLD"
    },
    "macd": {
      "main": 0.00041,
      "signal": 0.00049,
      "divergence": -8e-05,
      "histogram": "NEGATIVE",
      "trend": "BEARISH"
    },
    "bollinger_bands": {
      "upper": 1.17477,
      "middle": 1.17353,
      "lower": 1.17229,
      "price_position": "ABOVE_MIDDLE",
      "bandwidth": 0.00248
    },
    "moving_average": {
      "value": 1.17354,
      "price_position": "ABOVE",
      "signal": "BULLISH"
    },
    "parabolic_sar": {
      "value": 1.17499,
      "price_position": "BELOW",
      "trend": "DOWNTREND"
    },
    "ichimoku": {
      "tenkan_sen": 1.17364,
      "kijun_sen": 1.17347,
      "price_vs_tenkan": "ABOVE",
      "price_vs_kijun": "ABOVE",
      "tk_cross": "BULLISH"
    }
  },
  "indicator_insights": {
    "rsi": "Neutral at 55.0, consolidation or range-bound price action.",
    "mfi": "Balanced volume flow at 57.1, institutional activity moderate.",
    "stochastic": "Mid-range at 49.5, no extreme momentum detected.",
    "macd": "Bearish crossover above zero. Profit-taking phase, trend weakening.",
    "bollinger_bands": "Price holding above midline. Bullish bias maintained, support at 1.17353.",
    "moving_average": "Price 0.04% above MA. Uptrend confirmed, MA acting as dynamic support.",
    "parabolic_sar": "SAR positioned above price at 1.17499. Downtrend active, short positions favored.",
    "ichimoku": "Price above cloud components. Strong bullish structure, all systems aligned for longs."
  },
  "signals": {
    "primary": "NEUTRAL",
    "strength": "MODERATE",
    "recommendation": "OBSERVE"
  }
}